gecasmo/GCM.py
gecasmo/__init__.py
gecasmo/clickdefinitionreader.py
gecasmo/verboseprinter.py
gecasmo-0.0.1.dist-info/LICENSE
gecasmo-0.0.1.dist-info/METADATA
gecasmo-0.0.1.dist-info/WHEEL
gecasmo-0.0.1.dist-info/top_level.txt
gecasmo-0.0.1.dist-info/RECORD
