Metadata-Version: 2.1
Name: gecasmo
Version: 0.0.1
Summary: gecasmo is a package for estimating click models.
Home-page: https://github.com/cornederuijt/gecasmo
Author: Corné de Ruijt
Author-email: cornederuijt@gmail.com
License: MIT
Platform: UNKNOWN
Classifier: Topic :: Scientific/Engineering
Classifier: Intended Audience :: Science/Research
Classifier: Programming Language :: Python
Classifier: Development Status :: 4 - Beta
Classifier: License :: OSI Approved :: MIT License
Requires-Python: >=3.8
License-File: LICENSE
Requires-Dist: scikit-learn (>=0.23.2)
Requires-Dist: keras (>=2.4.3)
Requires-Dist: numpy (>=1.18.5)
